Metadata-Version: 1.1
Name: Flask-APScheduler
Version: 1.6.0
Summary: Adds APScheduler support to Flask
Home-page: https://github.com/viniciuschiele/flask-apscheduler
Author: Vinicius Chiele
Author-email: vinicius.chiele@gmail.com
License: Apache 2.0
Keywords: apscheduler,scheduler,scheduling,cron
Platform: UNKNOWN
Classifier: Development Status :: 5 - Production/Stable
Classifier: Intended Audience :: Developers
Classifier: Natural Language :: English
Classifier: Operating System :: OS Independent
Classifier: Programming Language :: Python
Classifier: Programming Language :: Python :: 2.7
Classifier: Programming Language :: Python :: 3
Classifier: Programming Language :: Python :: 3.3
Classifier: Programming Language :: Python :: 3.4
Classifier: Programming Language :: Python :: 3.5
